fastapix/__init__.py
fastapix/__main__.py
fastapix/context.py
fastapix/loader.py
fastapix/main.py
fastapix/py.typed
fastapix/commands/__init__.py
fastapix/commands/environment.py
fastapix/commands/middlewares.py
fastapix/commands/routes.py
fastapix/inference/__init__.py
fastapix/inference/analyzers.py
fastapix/inference/main.py
fastapix-0.1.0.dist-info/METADATA
fastapix-0.1.0.dist-info/WHEEL
fastapix-0.1.0.dist-info/entry_points.txt
fastapix-0.1.0.dist-info/licenses/LICENSE
fastapix-0.1.0.dist-info/RECORD
