Metadata-Version: 2.1
Name: fastapix
Version: 0.1.0
Summary: FastAPI X is a powerful CLI tool to help you! :rocket:
Project-URL: Homepage, https://github.com/Kludex/fastapix
Project-URL: Source, https://github.com/Kludex/fastapix
Project-URL: Twitter, https://twitter.com/marcelotryle
Project-URL: Funding, https://github.com/sponsors/Kludex
Author-email: Marcelo Trylesinski <marcelotryle@email.com>
License-File: LICENSE
Classifier: Development Status :: 3 - Alpha
Classifier: Intended Audience :: Developers
Classifier: License :: OSI Approved :: MIT License
Classifier: Natural Language :: English
Classifier: Operating System :: OS Independent
Classifier: Programming Language :: Python :: 3
Classifier: Programming Language :: Python :: 3 :: Only
Classifier: Programming Language :: Python :: 3.7
Classifier: Programming Language :: Python :: 3.8
Classifier: Programming Language :: Python :: 3.9
Classifier: Programming Language :: Python :: 3.10
Requires-Python: >=3.7
Requires-Dist: appdirs>=1.4.4
Requires-Dist: libcst>=0.4.7
Requires-Dist: pytablewriter>=0.64.2
Requires-Dist: rich>=12.6.0
Requires-Dist: typer>=0.6.1
